t2ebm/__init__.py
t2ebm/functions.py
t2ebm/graphs.py
t2ebm/llm.py
t2ebm/prompts.py
t2ebm/utils.py
t2ebm/version.py
t2ebm-0.1.2.dist-info/LICENSE
t2ebm-0.1.2.dist-info/METADATA
t2ebm-0.1.2.dist-info/WHEEL
t2ebm-0.1.2.dist-info/top_level.txt
t2ebm-0.1.2.dist-info/RECORD
