Metadata-Version: 2.1
Name: t2ebm
Version: 0.1.2
Summary: A Natural Language Interface to Explainable Boosting Machines
Home-page: https://github.com/interpretml/TalkToEBM
Author: Sebastian Bordt, Ben Lengerich, Harsha Nori, Rich Caruana
Author-email: sbordt@posteo.de
Classifier: Programming Language :: Python :: 3
Classifier: License :: OSI Approved :: MIT License
Classifier: Operating System :: OS Independent
Requires-Python: >=3.6
License-File: LICENSE
Requires-Dist: numpy (<2.0.0,>=1.14.0)
Requires-Dist: matplotlib
Requires-Dist: tiktoken
Requires-Dist: openai (>=1.8.0)
Requires-Dist: tenacity
Requires-Dist: scipy
Requires-Dist: interpret
